{
    "AddonsScoreURL": "NONE",
    "AddonsStatsURL": "https://freecad.org/addon_stats.json",
    "BlockedMacros": "BOLTS,WorkFeatures,how to install,documentation,PartsLibrary,FCGear",
    "CompositeSplitterState": "",
    "CustomRepoHash": "",
    "CustomRepositories": "",
    "CustomToolbarName": "Auto-Created Macro Toolbar",
    "DownloadMacros": false,
    "FirstTimeAskingForToolbar": true,
    "HideNonFSFFreeLibre": false,
    "HideNonOSIApproved": false,
    "HideUnlicensed": false,
    "KnownPythonVersions": "[]",
    "MacroUpdateStatsURL": "https://addons.freecad.org/macro_update_stats.json",
    "NoProxyCheck": true,
    "PackageTypeSelection": 0,
    "ProxyUrl": "",
    "SearchString": "",
    "SelectedAddon": "",
    "StatusSelection": 0,
    "SystemProxyCheck": false,
    "UserProxyCheck": false,
    "ViewStyle": 1,
    "WindowHeight": 600,
    "WindowWidth": 800,
    "addon_catalog_cache_url": "https://addons.freecad.org/addon_catalog_cache.zip",
    "alwaysAskForToolbar": true,
    "dontShowAddMacroButtonDialog": false,
    "force_git_in_repos": "parts_library",
    "last_fetched_addon_catalog_cache_hash": "Cache never fetched, no hash available",
    "last_fetched_macro_cache_hash": "Cache never fetched, no hash available",
    "macro_cache_url": "https://addons.freecad.org/macro_cache.zip",
    "old_backup_handling": "ask",
    "readWarning2022": false
}
